dce_lti_py-0.7.4.dist-info/DESCRIPTION.rst
dce_lti_py-0.7.4.dist-info/zip-safe
dce_lti_py-0.7.4.dist-info/top_level.txt
dce_lti_py-0.7.4.dist-info/metadata.json
dce_lti_py-0.7.4.dist-info/WHEEL
dce_lti_py-0.7.4.dist-info/RECORD
dce_lti_py-0.7.4.dist-info/METADATA
dce_lti_py/tool_consumer.py
dce_lti_py/__init__.py
dce_lti_py/tool_config.py
dce_lti_py/utils.py
dce_lti_py/outcome_response.py
dce_lti_py/tool_base.py
dce_lti_py/launch_params.py
dce_lti_py/tool_provider.py
dce_lti_py/outcome_request.py
dce_lti_py/contrib/__init__.py
dce_lti_py/contrib/flask/flask_tool_provider.py
dce_lti_py/contrib/flask/__init__.py
dce_lti_py/contrib/django/__init__.py
dce_lti_py/contrib/django/django_tool_provider.py
