Metadata-Version: 2.0
Name: dce-lti-py
Version: 0.7.4
Summary: A python library for building and/or consuming LTI apps
Home-page: https://github.com/harvard-dce/dce_lti_py
Author: Jay Luker
Author-email: jay_luker@harvard.edu
License: MIT License
Keywords: lti
Platform: UNKNOWN
Requires-Dist: lxml
Requires-Dist: oauthlib
Requires-Dist: requests-oauthlib
